SquareRoot2Py/RoundedSquareRoot2Py.py
SquareRoot2Py/SquareRoot2PyWithAdjustableRounding.py
SquareRoot2Py/__init__.py
SquareRoot2Py-2.1.0.dist-info/LICENSE
SquareRoot2Py-2.1.0.dist-info/METADATA
SquareRoot2Py-2.1.0.dist-info/WHEEL
SquareRoot2Py-2.1.0.dist-info/top_level.txt
SquareRoot2Py-2.1.0.dist-info/RECORD
