Metadata-Version: 2.1
Name: SquareRoot2Py
Version: 2.1.0
Summary: sqrt(2)
License: GNU GENERAL PUBLIC LICENSE
Project-URL: Homepage, https://github.com/tovicheung/SquareRoot2Py
Classifier: License :: OSI Approved :: MIT License
Classifier: Programming Language :: Python
Classifier: Programming Language :: Python :: 3
Classifier: Development Status :: 5 - Production/Stable
Classifier: Topic :: Scientific/Engineering :: Mathematics
License-File: LICENSE
